pdberellig/__main__.py
pdberellig/cli.py
pdberellig/conf/__init__.py
pdberellig/conf/conf.ini
pdberellig/core/__init__.py
pdberellig/core/cofactors.py
pdberellig/core/drugs.py
pdberellig/core/models.py
pdberellig/core/reactants.py
pdberellig/data/cofactors/cofactor_ec.csv
pdberellig/data/cofactors/cofactors_details.json
pdberellig/data/cofactors/representatives/ASC.cif
pdberellig/data/cofactors/representatives/B12.cif
pdberellig/data/cofactors/representatives/BTN.cif
pdberellig/data/cofactors/representatives/COA.cif
pdberellig/data/cofactors/representatives/COM.cif
pdberellig/data/cofactors/representatives/DPM.cif
pdberellig/data/cofactors/representatives/F43.cif
pdberellig/data/cofactors/representatives/FAD.cif
pdberellig/data/cofactors/representatives/FFO.cif
pdberellig/data/cofactors/representatives/FMN.cif
pdberellig/data/cofactors/representatives/GSH.cif
pdberellig/data/cofactors/representatives/H4B.cif
pdberellig/data/cofactors/representatives/HEA.cif
pdberellig/data/cofactors/representatives/LPA.cif
pdberellig/data/cofactors/representatives/MDO.cif
pdberellig/data/cofactors/representatives/MGD.cif
pdberellig/data/cofactors/representatives/MQ7.cif
pdberellig/data/cofactors/representatives/NAD.cif
pdberellig/data/cofactors/representatives/PLP.cif
pdberellig/data/cofactors/representatives/PNS.cif
pdberellig/data/cofactors/representatives/PQQ.cif
pdberellig/data/cofactors/representatives/SAM.cif
pdberellig/data/cofactors/representatives/TP7.cif
pdberellig/data/cofactors/representatives/TPP.cif
pdberellig/data/cofactors/representatives/TPQ.cif
pdberellig/data/cofactors/representatives/TRQ.cif
pdberellig/data/cofactors/representatives/UQ1.cif
pdberellig/data/cofactors/templates/0HG.sdf
pdberellig/data/cofactors/templates/1TY.sdf
pdberellig/data/cofactors/templates/ASC.sdf
pdberellig/data/cofactors/templates/B12.sdf
pdberellig/data/cofactors/templates/BTN.sdf
pdberellig/data/cofactors/templates/COAM.sdf
pdberellig/data/cofactors/templates/COM.sdf
pdberellig-1.0.1.dist-info/METADATA
pdberellig-1.0.1.dist-info/WHEEL
pdberellig-1.0.1.dist-info/entry_points.txt
pdberellig-1.0.1.dist-info/licenses/LICENSE
pdberellig-1.0.1.dist-info/RECORD
