Metadata-Version: 2.4
Name: pdberellig
Version: 1.0.1
Summary: A toolkit for functional annotation of ligands in the PDB
License: Apache 2.0
License-File: LICENSE
Keywords: PDB,ligand,cofactor,reactant,drug,annotation
Author: Ibrahim Roshan Kunnakkattu
Author-email: roshan@ebi.ac.uk
Requires-Python: >=3.10,<4.0
Classifier: Environment :: Console
Classifier: License :: Other/Proprietary License
Classifier: Programming Language :: Python :: 3
Classifier: Programming Language :: Python :: 3.10
Classifier: Programming Language :: Python :: 3.11
Classifier: Programming Language :: Python :: 3.12
Classifier: Programming Language :: Python :: 3.13
Classifier: Programming Language :: Python :: 3.14
Classifier: Topic :: Scientific/Engineering :: Bio-Informatics
Classifier: Topic :: Software Development :: Libraries :: Python Modules
Requires-Dist: click (==8.1.7)
Requires-Dist: pandas (>=2.2.3,<3.0.0)
Requires-Dist: pdbeccdutils (>=0.8.6,<0.9.0)
Requires-Dist: sparqlwrapper (>=2.0.0,<3.0.0)
Project-URL: Repository, https://github.com/PDBeurope/rellig
